{
    "state_str": "08b900/b9705a",
    "state_str_content_free": "dd1dd1/e08801",
    "foreground_activity": "com.tudorspan.recipekeeper/crc6494081064acdf378e.CookbookPage",
    "activity_stack": [
        "com.tudorspan.recipekeeper/crc6494081064acdf378e.CookbookPage",
        "com.tudorspan.recipekeeper/crc6494081064acdf378e.HomePage"
    ],
    "width": 2340,
    "height": 1080,
    "views": [
        {
            "package": "com.tudorspan.recipekeeper",
            "visible": true,
            "checkable": false,
            "child_count": 2,
            "editable": false,
            "clickable": false,
            "is_password": false,
            "focusable": false,
            "enabled": true,
            "content_description": null,
            "children": [
                1,
                16
            ],
            "focused": false,
            "bounds": [
                [
                    0,
                    0
                ],
                [
                    1080,
                    1920
                ]
            ],
            "resource_id": null,
            "checked": false,
            "text": null,
            "class": "android.widget.FrameLayout",
            "scrollable": false,
            "selected": false,
            "long_clickable": false,
            "parent": -1,
            "temp_id": 0,
            "size": "1080*1920",
            "signature": "[class]android.widget.FrameLayout[resource_id]None[text]None[enabled,,]",
            "view_str": "42a68e99d7f19591827b6cf68d844a8d",
            "bound_box": "0,0,1080,1920",
            "content_free_signature": "[class]android.widget.FrameLayout[resource_id]None"
        },
        {
            "package": "com.tudorspan.recipekeeper",
            "visible": true,
            "checkable": false,
            "child_count": 1,
            "editable": false,
            "clickable": false,
            "is_password": false,
            "focusable": false,
            "enabled": true,
            "content_description": null,
            "children": [
                2
            ],
            "focused": false,
            "bounds": [
                [
                    0,
                    0
                ],
                [
                    1080,
                    1776
                ]
            ],
            "resource_id": null,
            "checked": false,
            "text": null,
            "class": "android.widget.LinearLayout",
            "scrollable": false,
            "selected": false,
            "long_clickable": false,
            "parent": 0,
            "temp_id": 1,
            "size": "1080*1776",
            "signature": "[class]android.widget.LinearLayout[resource_id]None[text]None[enabled,,]",
            "view_str": "046ea3c004351c324739e7d52cd8838d",
            "bound_box": "0,0,1080,1776",
            "content_free_signature": "[class]android.widget.LinearLayout[resource_id]None"
        },
        {
            "package": "com.tudorspan.recipekeeper",
            "visible": true,
            "checkable": false,
            "child_count": 1,
            "editable": false,
            "clickable": false,
            "is_password": false,
            "focusable": false,
            "enabled": true,
            "content_description": null,
            "children": [
                3
            ],
            "focused": false,
            "bounds": [
                [
                    0,
                    72
                ],
                [
                    1080,
                    1776
                ]
            ],
            "resource_id": null,
            "checked": false,
            "text": null,
            "class": "android.widget.FrameLayout",
            "scrollable": false,
            "selected": false,
            "long_clickable": false,
            "parent": 1,
            "temp_id": 2,
            "size": "1080*1704",
            "signature": "[class]android.widget.FrameLayout[resource_id]None[text]None[enabled,,]",
            "view_str": "7edcf0791e03031b875895b3fecb152b",
            "bound_box": "0,72,1080,1776",
            "content_free_signature": "[class]android.widget.FrameLayout[resource_id]None"
        },
        {
            "package": "com.tudorspan.recipekeeper",
            "visible": true,
            "checkable": false,
            "child_count": 1,
            "editable": false,
            "clickable": false,
            "is_password": false,
            "focusable": false,
            "enabled": true,
            "content_description": null,
            "children": [
                4
            ],
            "focused": false,
            "bounds": [
                [
                    0,
                    72
                ],
                [
                    1080,
                    1776
                ]
            ],
            "resource_id": "com.tudorspan.recipekeeper:id/action_bar_root",
            "checked": false,
            "text": null,
            "class": "android.widget.LinearLayout",
            "scrollable": false,
            "selected": false,
            "long_clickable": false,
            "parent": 2,
            "temp_id": 3,
            "size": "1080*1704",
            "signature": "[class]android.widget.LinearLayout[resource_id]com.tudorspan.recipekeeper:id/action_bar_root[text]None[enabled,,]",
            "view_str": "efcbdfa540362abc2bbdca1efc009082",
            "bound_box": "0,72,1080,1776",
            "content_free_signature": "[class]android.widget.LinearLayout[resource_id]com.tudorspan.recipekeeper:id/action_bar_root"
        },
        {
            "package": "com.tudorspan.recipekeeper",
            "visible": true,
            "checkable": false,
            "child_count": 1,
            "editable": false,
            "clickable": false,
            "is_password": false,
            "focusable": false,
            "enabled": true,
            "content_description": null,
            "children": [
                5
            ],
            "focused": false,
            "bounds": [
                [
                    0,
                    72
                ],
                [
                    1080,
                    1776
                ]
            ],
            "resource_id": "android:id/content",
            "checked": false,
            "text": null,
            "class": "android.widget.FrameLayout",
            "scrollable": false,
            "selected": false,
            "long_clickable": false,
            "parent": 3,
            "temp_id": 4,
            "size": "1080*1704",
            "signature": "[class]android.widget.FrameLayout[resource_id]android:id/content[text]None[enabled,,]",
            "view_str": "2f6001c20d0497aa40ee77fba7e9d195",
            "bound_box": "0,72,1080,1776",
            "content_free_signature": "[class]android.widget.FrameLayout[resource_id]android:id/content"
        },
        {
            "package": "com.tudorspan.recipekeeper",
            "visible": true,
            "checkable": false,
            "child_count": 1,
            "editable": false,
            "clickable": false,
            "is_password": false,
            "focusable": true,
            "enabled": true,
            "content_description": null,
            "children": [
                6
            ],
            "focused": false,
            "bounds": [
                [
                    0,
                    72
                ],
                [
                    1080,
                    1776
                ]
            ],
            "resource_id": null,
            "checked": false,
            "text": null,
            "class": "android.widget.LinearLayout",
            "scrollable": false,
            "selected": false,
            "long_clickable": false,
            "parent": 4,
            "temp_id": 5,
            "size": "1080*1704",
            "signature": "[class]android.widget.LinearLayout[resource_id]None[text]None[enabled,,]",
            "view_str": "c3fdfca99c5bf91189bc323e8d8d88c7",
            "bound_box": "0,72,1080,1776",
            "content_free_signature": "[class]android.widget.LinearLayout[resource_id]None"
        },
        {
            "package": "com.tudorspan.recipekeeper",
            "visible": true,
            "checkable": false,
            "child_count": 2,
            "editable": false,
            "clickable": false,
            "is_password": false,
            "focusable": false,
            "enabled": true,
            "content_description": null,
            "children": [
                7,
                12
            ],
            "focused": false,
            "bounds": [
                [
                    0,
                    72
                ],
                [
                    1080,
                    1776
                ]
            ],
            "resource_id": null,
            "checked": false,
            "text": null,
            "class": "android.widget.FrameLayout",
            "scrollable": false,
            "selected": false,
            "long_clickable": false,
            "parent": 5,
            "temp_id": 6,
            "size": "1080*1704",
            "signature": "[class]android.widget.FrameLayout[resource_id]None[text]None[enabled,,]",
            "view_str": "d6d8b6765e977abc0313cb3e068ebc0e",
            "bound_box": "0,72,1080,1776",
            "content_free_signature": "[class]android.widget.FrameLayout[resource_id]None"
        },
        {
            "package": "com.tudorspan.recipekeeper",
            "visible": true,
            "checkable": false,
            "child_count": 1,
            "editable": false,
            "clickable": false,
            "is_password": false,
            "focusable": false,
            "enabled": true,
            "content_description": null,
            "children": [
                8
            ],
            "focused": false,
            "bounds": [
                [
                    0,
                    72
                ],
                [
                    1080,
                    1776
                ]
            ],
            "resource_id": null,
            "checked": false,
            "text": null,
            "class": "android.widget.LinearLayout",
            "scrollable": false,
            "selected": false,
            "long_clickable": false,
            "parent": 6,
            "temp_id": 7,
            "size": "1080*1704",
            "signature": "[class]android.widget.LinearLayout[resource_id]None[text]None[enabled,,]",
            "view_str": "023db9ced324817be65a3fbb63215d01",
            "bound_box": "0,72,1080,1776",
            "content_free_signature": "[class]android.widget.LinearLayout[resource_id]None"
        },
        {
            "package": "com.tudorspan.recipekeeper",
            "visible": true,
            "checkable": false,
            "child_count": 3,
            "editable": false,
            "clickable": false,
            "is_password": false,
            "focusable": false,
            "enabled": true,
            "content_description": null,
            "children": [
                9,
                10,
                11
            ],
            "focused": false,
            "bounds": [
                [
                    0,
                    72
                ],
                [
                    1080,
                    240
                ]
            ],
            "resource_id": "com.tudorspan.recipekeeper:id/toolbar",
            "checked": false,
            "text": null,
            "class": "android.view.ViewGroup",
            "scrollable": false,
            "selected": false,
            "long_clickable": false,
            "parent": 7,
            "temp_id": 8,
            "size": "1080*168",
            "signature": "[class]android.view.ViewGroup[resource_id]com.tudorspan.recipekeeper:id/toolbar[text]None[enabled,,]",
            "view_str": "bc15ad0223db06bd577ad6c483f6dd12",
            "bound_box": "0,72,1080,240",
            "content_free_signature": "[class]android.view.ViewGroup[resource_id]com.tudorspan.recipekeeper:id/toolbar"
        },
        {
            "package": "com.tudorspan.recipekeeper",
            "visible": true,
            "checkable": false,
            "child_count": 0,
            "editable": false,
            "clickable": true,
            "is_password": false,
            "focusable": true,
            "enabled": true,
            "content_description": "Navigate up",
            "children": [],
            "focused": false,
            "bounds": [
                [
                    0,
                    72
                ],
                [
                    168,
                    240
                ]
            ],
            "resource_id": null,
            "checked": false,
            "text": null,
            "class": "android.widget.ImageButton",
            "scrollable": false,
            "selected": false,
            "long_clickable": false,
            "parent": 8,
            "temp_id": 9,
            "size": "168*168",
            "signature": "[class]android.widget.ImageButton[resource_id]None[text]None[enabled,,]",
            "view_str": "da36cac04ade7c8cd955233f6c022b24",
            "bound_box": "0,72,168,240",
            "content_free_signature": "[class]android.widget.ImageButton[resource_id]None",
            "allowed_actions": [
                "touch"
            ],
            "status": [],
            "local_id": "0",
            "desc": "<button alt='Navigate up' bound_box=0,72,168,240></button>"
        },
        {
            "package": "com.tudorspan.recipekeeper",
            "visible": true,
            "checkable": false,
            "child_count": 0,
            "editable": false,
            "clickable": false,
            "is_password": false,
            "focusable": false,
            "enabled": true,
            "content_description": null,
            "children": [],
            "focused": false,
            "bounds": [
                [
                    216,
                    115
                ],
                [
                    518,
                    196
                ]
            ],
            "resource_id": null,
            "checked": false,
            "text": "Cookbooks",
            "class": "android.widget.TextView",
            "scrollable": false,
            "selected": false,
            "long_clickable": false,
            "parent": 8,
            "temp_id": 10,
            "size": "302*81",
            "signature": "[class]android.widget.TextView[resource_id]None[text]Cookbooks[enabled,,]",
            "view_str": "0ef6a9c5eb8ba88ea03ad45d664c5cb5",
            "bound_box": "216,115,518,196",
            "content_free_signature": "[class]android.widget.TextView[resource_id]None",
            "allowed_actions": [
                "touch"
            ],
            "status": [],
            "local_id": "1",
            "desc": "<p bound_box=216,115,518,196>Cookbooks</p>"
        },
        {
            "package": "com.tudorspan.recipekeeper",
            "visible": false,
            "checkable": false,
            "child_count": 0,
            "editable": false,
            "clickable": false,
            "is_password": false,
            "focusable": false,
            "enabled": true,
            "content_description": null,
            "children": [],
            "focused": false,
            "bounds": [
                [
                    1080,
                    72
                ],
                [
                    1080,
                    240
                ]
            ],
            "resource_id": null,
            "checked": false,
            "text": null,
            "class": "androidx.appcompat.widget.LinearLayoutCompat",
            "scrollable": false,
            "selected": false,
            "long_clickable": false,
            "parent": 8,
            "temp_id": 11,
            "size": "0*168",
            "signature": "[class]androidx.appcompat.widget.LinearLayoutCompat[resource_id]None[text]None[enabled,,]",
            "view_str": "ef5aa655021abadb10cac8089b61a6c4",
            "bound_box": "1080,72,1080,240",
            "content_free_signature": "[class]androidx.appcompat.widget.LinearLayoutCompat[resource_id]None"
        },
        {
            "package": "com.tudorspan.recipekeeper",
            "visible": true,
            "checkable": false,
            "child_count": 3,
            "editable": false,
            "clickable": false,
            "is_password": false,
            "focusable": false,
            "enabled": true,
            "content_description": null,
            "children": [
                13,
                14,
                15
            ],
            "focused": false,
            "bounds": [
                [
                    0,
                    72
                ],
                [
                    1080,
                    1776
                ]
            ],
            "resource_id": "com.tudorspan.recipekeeper:id/lnrNoCookbooks",
            "checked": false,
            "text": null,
            "class": "android.widget.LinearLayout",
            "scrollable": false,
            "selected": false,
            "long_clickable": false,
            "parent": 6,
            "temp_id": 12,
            "size": "1080*1704",
            "signature": "[class]android.widget.LinearLayout[resource_id]com.tudorspan.recipekeeper:id/lnrNoCookbooks[text]None[enabled,,]",
            "view_str": "f49be04c30296b9e29b701fcc4cc2984",
            "bound_box": "0,72,1080,1776",
            "content_free_signature": "[class]android.widget.LinearLayout[resource_id]com.tudorspan.recipekeeper:id/lnrNoCookbooks"
        },
        {
            "package": "com.tudorspan.recipekeeper",
            "visible": true,
            "checkable": false,
            "child_count": 0,
            "editable": false,
            "clickable": false,
            "is_password": false,
            "focusable": false,
            "enabled": true,
            "content_description": null,
            "children": [],
            "focused": false,
            "bounds": [
                [
                    420,
                    578
                ],
                [
                    660,
                    818
                ]
            ],
            "resource_id": "com.tudorspan.recipekeeper:id/imgCookbook",
            "checked": false,
            "text": null,
            "class": "android.widget.ImageView",
            "scrollable": false,
            "selected": false,
            "long_clickable": false,
            "parent": 12,
            "temp_id": 13,
            "size": "240*240",
            "signature": "[class]android.widget.ImageView[resource_id]com.tudorspan.recipekeeper:id/imgCookbook[text]None[enabled,,]",
            "view_str": "b56536fd649f37400712a603b989176b",
            "bound_box": "420,578,660,818",
            "content_free_signature": "[class]android.widget.ImageView[resource_id]com.tudorspan.recipekeeper:id/imgCookbook"
        },
        {
            "package": "com.tudorspan.recipekeeper",
            "visible": true,
            "checkable": false,
            "child_count": 0,
            "editable": false,
            "clickable": false,
            "is_password": false,
            "focusable": false,
            "enabled": true,
            "content_description": null,
            "children": [],
            "focused": false,
            "bounds": [
                [
                    48,
                    866
                ],
                [
                    1032,
                    1102
                ]
            ],
            "resource_id": "com.tudorspan.recipekeeper:id/txtNoCookbookDescription",
            "checked": false,
            "text": "Create a beautiful cookbook of your recipes for printing or sharing as a PDF with cover page, table of contents, custom layouts and more.",
            "class": "android.widget.TextView",
            "scrollable": false,
            "selected": false,
            "long_clickable": false,
            "parent": 12,
            "temp_id": 14,
            "size": "984*236",
            "signature": "[class]android.widget.TextView[resource_id]com.tudorspan.recipekeeper:id/txtNoCookbookDescription[text]None[enabled,,]",
            "view_str": "e2f35fc4506c90aec14e832f81d0a43e",
            "bound_box": "48,866,1032,1102",
            "content_free_signature": "[class]android.widget.TextView[resource_id]com.tudorspan.recipekeeper:id/txtNoCookbookDescription",
            "allowed_actions": [
                "touch"
            ],
            "status": [],
            "local_id": "2",
            "desc": "<p bound_box=48,866,1032,1102>Create a beautiful cookbook of your recipes for pr</p>"
        },
        {
            "package": "com.tudorspan.recipekeeper",
            "visible": true,
            "checkable": false,
            "child_count": 0,
            "editable": false,
            "clickable": true,
            "is_password": false,
            "focusable": true,
            "enabled": true,
            "content_description": null,
            "children": [],
            "focused": false,
            "bounds": [
                [
                    311,
                    1126
                ],
                [
                    768,
                    1270
                ]
            ],
            "resource_id": "com.tudorspan.recipekeeper:id/btnCreateCookbook",
            "checked": false,
            "text": "CREATE COOKBOOK",
            "class": "android.widget.Button",
            "scrollable": false,
            "selected": false,
            "long_clickable": false,
            "parent": 12,
            "temp_id": 15,
            "size": "457*144",
            "signature": "[class]android.widget.Button[resource_id]com.tudorspan.recipekeeper:id/btnCreateCookbook[text]CREATE COOKBOOK[enabled,,]",
            "view_str": "4127873497deab566f8398feb51ec3bd",
            "bound_box": "311,1126,768,1270",
            "content_free_signature": "[class]android.widget.Button[resource_id]com.tudorspan.recipekeeper:id/btnCreateCookbook",
            "allowed_actions": [
                "touch"
            ],
            "status": [],
            "local_id": "3",
            "desc": "<button bound_box=311,1126,768,1270>CREATE COOKBOOK</button>"
        },
        {
            "package": "com.tudorspan.recipekeeper",
            "visible": false,
            "checkable": false,
            "child_count": 0,
            "editable": false,
            "clickable": false,
            "is_password": false,
            "focusable": false,
            "enabled": true,
            "content_description": null,
            "children": [],
            "focused": false,
            "bounds": [
                [
                    0,
                    1776
                ],
                [
                    1080,
                    1920
                ]
            ],
            "resource_id": "android:id/navigationBarBackground",
            "checked": false,
            "text": null,
            "class": "android.view.View",
            "scrollable": false,
            "selected": false,
            "long_clickable": false,
            "parent": 0,
            "temp_id": 16,
            "size": "1080*144",
            "signature": "[class]android.view.View[resource_id]android:id/navigationBarBackground[text]None[enabled,,]",
            "view_str": "e27e243f3091a9c87631b064c6fd3d4f",
            "bound_box": "0,1776,1080,1920",
            "content_free_signature": "[class]android.view.View[resource_id]android:id/navigationBarBackground"
        }
    ]
}